pydelivengo/__init__.py
pydelivengo/exception.py
pydelivengo/pydelivengo.py
pydelivengo-1.6.dist-info/LICENSE
pydelivengo-1.6.dist-info/METADATA
pydelivengo-1.6.dist-info/WHEEL
pydelivengo-1.6.dist-info/top_level.txt
pydelivengo-1.6.dist-info/RECORD
