Metadata-Version: 2.1
Name: pydelivengo
Version: 1.6
Summary: A lib to use MyDelivengo API
Home-page: https://github.com/alexandriagroup/pydelivengo
Author: Alicia FLOREZ
Author-email: alicflorez@gmail.com
License: MIT
Project-URL: Source, https://github.com/alexandriagroup/pydelivengo/archive/v1.5.tar.gz
Project-URL: Documentation, https://alexandriagroup.github.io/pydelivengo/
Project-URL: Travis, https://travis-ci.org/alexandriagroup/pydelivengo
Keywords: api mydelivengo python3 webservices
Platform: UNKNOWN
Classifier: Programming Language :: Python :: 3
Classifier: License :: OSI Approved :: MIT License
Classifier: Operating System :: OS Independent
Classifier: Development Status :: 5 - Production/Stable
License-File: LICENSE
